de_console_client/__init__.py
de_console_client/api_client.py
de_console_client/api_response.py
de_console_client/configuration.py
de_console_client/exceptions.py
de_console_client/py.typed
de_console_client/rest.py
de_console_client/api/__init__.py
de_console_client/api/chromia_entity_db_api.py
de_console_client/api/chromia_file_storage_api.py
de_console_client/api/chromia_vector_db_api.py
de_console_client/models/__init__.py
de_console_client/models/create_vector_batch_request.py
de_console_client/models/create_vector_request.py
de_console_client/models/delete_file_batch_request.py
de_console_client/models/download_file_batch_request.py
de_console_client/models/download_file_batch_response.py
de_console_client/models/download_file_response.py
de_console_client/models/entities_record_counts.py
de_console_client/models/entities_record_counts_counts_value.py
de_console_client/models/entity_field.py
de_console_client/models/entity_list_response.py
de_console_client/models/entity_schema.py
de_console_client/models/error_detail.py
de_console_client/models/error_response.py
de_console_client/models/get_closest_response.py
de_console_client/models/image_embedding_batch_request.py
de_console_client/models/image_embedding_request.py
de_console_client/models/message_with_signer_response.py
de_console_client/models/news_headline_with_embedding.py
de_console_client/models/paginated_result.py
de_console_client/models/payload_distance.py
de_console_client/models/payload_with_metadata.py
de_console_client/models/record_list_response.py
de_console_client/models/record_response.py
de_console_client/models/search_objects_request.py
de_console_client/models/transaction_result_body.py
de_console_client/models/upload_file_batch_request.py
de_console_client/models/upload_file_batch_response.py
de_console_client/models/upload_file_request.py
de_console_client/models/upload_file_response.py
de_console_client/models/user_file_list_response.py
de_console_client/models/user_file_response.py
de_console_client-0.2.3.dist-info/METADATA
de_console_client-0.2.3.dist-info/WHEEL
de_console_client-0.2.3.dist-info/top_level.txt
de_console_client-0.2.3.dist-info/RECORD
