Metadata-Version: 2.4
Name: de_console_client
Version: 0.2.3
Summary: Chromia Console API with Swagger UI
Home-page: https://gitlab.com/chromaway/core-tools/chromia-console
Author: Chromaway
Author-email: Chromaway <devex@chromaway.com>
Project-URL: Repository, https://gitlab.com/chromaway/core-tools/chromia-console
Project-URL: Homepage, https://chromia.com
Project-URL: Documentation, https://docs.chromia.com
Keywords: Chromia,Vector Database,Semantic Search,Embeddings,Blockchain
Requires-Python: >= 3.9
Requires-Dist: urllib3<3.0.0,>=2.1.0
Requires-Dist: python-dateutil>=2.8.2
Requires-Dist: pydantic>=2
Requires-Dist: typing-extensions>=4.7.1
Dynamic: author
Dynamic: home-page
Dynamic: requires-python
